src/__init__.py
src/activation_functions.py
src/matrix_math.py
src/nn.py
SwiftNet-0.0.10.dist-info/METADATA
SwiftNet-0.0.10.dist-info/WHEEL
SwiftNet-0.0.10.dist-info/top_level.txt
SwiftNet-0.0.10.dist-info/RECORD
